DAY_3/MUX_16X1_USING4X1AND2X1MUX/mux_16x1.v
module mux_2x1(input[1:0]a,input sel,output reg  y);
always @(*)begin
case (sel)
1'b0:y=a[0];
1'b1:y=a[1];
endcase
end
endmodule
module mux_4x1 (input [3:0]a,input [1:0]sel,output reg y);
always @(*)begin
case (sel)
2'b00:y=a[0];
2'b01:y=a[1];
2'b10:y=a[2];
2'b11:y=a[3];
endcase
end
endmodule
module mux_16x1(input[15:0]a,input[3:0]sel,output wire  y);
wire w1,w2,w3,w4,q1,q2;
mux_4x1 m1 (.a(a[3:0]),   .sel(sel[1:0]), .y(w1));
mux_4x1 m2 (.a(a[7:4]),   .sel(sel[1:0]), .y(w2));
mux_4x1 m3 (.a(a[11:8]),  .sel(sel[1:0]), .y(w3));
mux_4x1 m4 (.a(a[15:12]), .sel(sel[1:0]), .y(w4));
mux_2x1 m5 (.a({w2, w1}), .sel(sel[2]), .y(q1));
mux_2x1 m6 (.a({w4, w3}), .sel(sel[2]), .y(q2));
mux_2x1 m7 (.a({q2, q1}), .sel(sel[3]), .y(y));
endmodule

DAY_3/MUX_16X1_USING4X1AND2X1MUX/mux_16x1_tb.v
module mux_16x1_tb();
reg [15:0]a;
reg [3:0]sel;
wire y;
mux_16x1 dut(.a(a),.sel(sel),.y(y));
initial begin
$monitor("input=%b | mode=%b | output=%b",a,sel,y);
$dumpfile("mux_16x1.vcd");
$dumpvars();
a=16'd42791;
sel=4'd0;#10;
sel=4'd1;#10;
sel=4'd2;#10;
sel=4'd3;#10;
sel=4'd4;#10;
sel=4'd5;#10;
sel=4'd6;#10;
sel=4'd7;#10;
sel=4'd8;#10;
sel=4'd9;#10;
sel=4'd10;#10;
sel=4'd11;#10;
sel=4'd12;#10;
sel=4'd13;#10;
sel=4'd14;#10;
sel=4'd15;#10;
$finish;
end 
endmodule

DAY_3/MUX_16X1_USING4X1AND2X1MUX/mux_16x1.vcd
$date
	Tue Dec 16 19:42:01 2025
$end
$version
	Icarus Verilog
$end
$timescale
	1s
$end
$scope module mux_16x1_tb $end
$var wire 1 ! y $end
$var reg 16 " a [15:0] $end
$var reg 4 # sel [3:0] $end
$scope module dut $end
$var wire 16 $ a [15:0] $end
$var wire 4 % sel [3:0] $end
$var wire 1 ! y $end
$var wire 1 & w4 $end
$var wire 1 ' w3 $end
$var wire 1 ( w2 $end
$var wire 1 ) w1 $end
$var wire 1 * q2 $end
$var wire 1 + q1 $end
$scope module m1 $end
$var wire 4 , a [3:0] $end
$var wire 2 - sel [1:0] $end
$var reg 1 ) y $end
$upscope $end
$scope module m2 $end
$var wire 4 . a [3:0] $end
$var wire 2 / sel [1:0] $end
$var reg 1 ( y $end
$upscope $end
$scope module m3 $end
$var wire 4 0 a [3:0] $end
$var wire 2 1 sel [1:0] $end
$var reg 1 ' y $end
$upscope $end
$scope module m4 $end
$var wire 4 2 a [3:0] $end
$var wire 2 3 sel [1:0] $end
$var reg 1 & y $end
$upscope $end
$scope module m5 $end
$var wire 2 4 a [1:0] $end
$var wire 1 5 sel $end
$var reg 1 + y $end
$upscope $end
$scope module m6 $end
$var wire 2 6 a [1:0] $end
$var wire 1 7 sel $end
$var reg 1 * y $end
$upscope $end
$scope module m7 $end
$var wire 2 8 a [1:0] $end
$var wire 1 9 sel $end
$var reg 1 ! y $end
$upscope $end
$upscope $end
$upscope $end
$enddefinitions $end
$comment Show the parameter values. $end
$dumpall
$end
#0
$dumpvars
09
b11 8
07
b1 6
05
b1 4
b0 3
b1010 2
b0 1
b111 0
b0 /
b10 .
b0 -
b111 ,
1+
1*
1)
0(
1'
0&
b0 %
b1010011100100111 $
b0 #
b1010011100100111 "
1!
$end
#10
b11 4
1(
b11 6
1&
b1 -
b1 /
b1 1
b1 3
b1 #
b1 %
#20
b1 4
0(
b1 6
0&
b10 -
b10 /
b10 1
b10 3
b10 #
b10 %
#30
0!
0+
b0 8
0*
b0 4
0)
0'
b10 6
1&
b11 -
b11 /
b11 1
b11 3
b11 #
b11 %
#40
b1 4
1)
1'
b1 6
0&
b0 8
0*
b0 -
b0 /
b0 1
b0 3
15
17
b100 #
b100 %
#50
1!
1+
b11 8
1*
b11 4
1(
b11 6
1&
b1 -
b1 /
b1 1
b1 3
b101 #
b101 %
#60
0!
0+
b0 8
0*
b1 4
0(
b1 6
0&
b10 -
b10 /
b10 1
b10 3
b110 #
b110 %
#70
b10 8
1*
b0 4
0)
0'
b10 6
1&
b11 -
b11 /
b11 1
b11 3
b111 #
b111 %
#80
1+
b1 4
1)
1'
b1 6
0&
b11 8
1*
1!
b0 -
b0 /
b0 1
b0 3
05
07
19
b1000 #
b1000 %
#90
b11 4
1(
b11 6
1&
b1 -
b1 /
b1 1
b1 3
b1001 #
b1001 %
#100
b1 4
0(
b1 6
0&
b10 -
b10 /
b10 1
b10 3
b1010 #
b1010 %
#110
0!
0+
b0 8
0*
b0 4
0)
0'
b10 6
1&
b11 -
b11 /
b11 1
b11 3
b1011 #
b1011 %
#120
0!
b1 4
1)
1'
b1 6
0&
b0 8
0*
b0 -
b0 /
b0 1
b0 3
15
17
b1100 #
b1100 %
#130
1!
1+
b11 8
1*
b11 4
1(
b11 6
1&
b1 -
b1 /
b1 1
b1 3
b1101 #
b1101 %
#140
0!
0+
b0 8
0*
b1 4
0(
b1 6
0&
b10 -
b10 /
b10 1
b10 3
b1110 #
b1110 %
#150
1!
b10 8
1*
b0 4
0)
0'
b10 6
1&
b11 -
b11 /
b11 1
b11 3
b1111 #
b1111 %
