siso.v
module siso(
input clk,
input rst,
input s_in,
output s_out);
reg [3:0] shift_reg;
always @(posedge clk) begin
   if(rst)
      shift_reg <=4'b0000;
  else 
        shift_reg <= {shift_reg[2:0], s_in};
end
assign s_out = shift_reg[3];
endmodule

siso_tb.v
module siso_tb;
reg s_in,clk,rst;
wire s_out;
siso dut(.clk(clk),.rst(rst),.s_in(s_in),.s_out(s_out));
always #5 clk=~clk;
initial begin
$monitor("s_in=%b | s_out=%b | time=%0t",s_in,s_out,$time);
$dumpfile("siso.vcd");
$dumpvars(0);
clk=0;
rst=1;
s_in=0;

rst=0;#10;
s_in=1;#10;
s_in=0;#10;
s_in=1;#10;
s_in=0;#10;
s_in=1;#10;
$finish;
end 
endmodule

siso.vcd
$date
	Mon Dec 22 11:29:11 2025
$end
$version
	Icarus Verilog
$end
$timescale
	1s
$end
$scope module siso_tb $end
$var wire 1 ! s_out $end
$var reg 1 " clk $end
$var reg 1 # rst $end
$var reg 1 $ s_in $end
$scope module dut $end
$var wire 1 " clk $end
$var wire 1 # rst $end
$var wire 1 $ s_in $end
$var wire 1 ! s_out $end
$var reg 4 % shift_reg [3:0] $end
$upscope $end
$upscope $end
$enddefinitions $end
$comment Show the parameter values. $end
$dumpall
$end
#0
$dumpvars
bx %
0$
0#
0"
x!
$end
#5
bx0 %
1"
#10
0"
1$
#15
bx01 %
1"
#20
0"
0$
#25
bx010 %
1"
#30
0"
1$
#35
0!
b101 %
1"
#40
0"
0$
#45
1!
b1010 %
1"
#50
0"
1$
#55
0!
b101 %
1"
