DAY_1O/COUNTERS/UPDOWN COUNTER/updown_counter.v
module updown_counter(
 input clk,
 input rst,
 input up,
 output reg [3:0]count);
always @(posedge clk or posedge rst)begin
if(rst)
     count<=4'b0000;
else if (up)
      count<=count+1'b1;
else
      count<=count-1'b1;
end
endmodule

DAY_1O/COUNTERS/UPDOWN COUNTER/updown_counter_tb.v
module updown_counter_tb;
reg clk;
reg rst;
reg up;
wire [3:0]count;
updown_counter dut(.clk(clk),.rst(rst),.up(up),.count(count));
always #5 clk=~clk;
initial begin
$dumpfile("updown_counter.vcd");
$dumpvars(0,updown_counter_tb);
$monitor("count=%b | up=%b | time=%0t", count, up, $time);
clk=0;
rst=1;#10;
up=1;

rst=0;#10;

up=0;#100;
up=1;#100;

#300 $finish;

end
endmodule

DAY_1O/COUNTERS/UPDOWN COUNTER/updown_counter.vcd
$date
	Fri Dec 26 03:53:13 2025
$end
$version
	Icarus Verilog
$end
$timescale
	1s
$end
$scope module updown_counter_tb $end
$var wire 4 ! count [3:0] $end
$var reg 1 " clk $end
$var reg 1 # rst $end
$var reg 1 $ up $end
$scope module dut $end
$var wire 1 " clk $end
$var wire 1 # rst $end
$var wire 1 $ up $end
$var reg 4 % count [3:0] $end
$upscope $end
$upscope $end
$enddefinitions $end
$comment Show the parameter values. $end
$dumpall
$end
#0
$dumpvars
b0 %
x$
1#
0"
b0 !
$end
#5
1"
#10
0"
0#
1$
#15
b1 !
b1 %
1"
#20
0"
0$
#25
b0 !
b0 %
1"
#30
0"
#35
b1111 !
b1111 %
1"
#40
0"
#45
b1110 !
b1110 %
1"
#50
0"
#55
b1101 !
b1101 %
1"
#60
0"
#65
b1100 !
b1100 %
1"
#70
0"
#75
b1011 !
b1011 %
1"
#80
0"
#85
b1010 !
b1010 %
1"
#90
0"
#95
b1001 !
b1001 %
1"
#100
0"
#105
b1000 !
b1000 %
1"
#110
0"
#115
b111 !
b111 %
1"
#120
0"
1$
#125
b1000 !
b1000 %
1"
#130
0"
#135
b1001 !
b1001 %
1"
#140
0"
#145
b1010 !
b1010 %
1"
#150
0"
#155
b1011 !
b1011 %
1"
#160
0"
#165
b1100 !
b1100 %
1"
#170
0"
#175
b1101 !
b1101 %
1"
#180
0"
#185
b1110 !
b1110 %
1"
#190
0"
#195
b1111 !
b1111 %
1"
#200
0"
#205
b0 !
b0 %
1"
#210
0"
#215
b1 !
b1 %
1"
#220
0"
#225
b10 !
b10 %
1"
#230
0"
#235
b11 !
b11 %
1"
#240
0"
#245
b100 !
b100 %
1"
#250
0"
#255
b101 !
b101 %
1"
#260
0"
#265
b110 !
b110 %
1"
#270
0"
#275
b111 !
b111 %
1"
#280
0"
#285
b1000 !
b1000 %
1"
#290
0"
#295
b1001 !
b1001 %
1"
#300
0"
#305
b1010 !
b1010 %
1"
#310
0"
#315
b1011 !
b1011 %
1"
#320
0"
#325
b1100 !
b1100 %
1"
#330
0"
#335
b1101 !
b1101 %
1"
#340
0"
#345
b1110 !
b1110 %
1"
#350
0"
#355
b1111 !
b1111 %
1"
#360
0"
#365
b0 !
b0 %
1"
#370
0"
#375
b1 !
b1 %
1"
#380
0"
#385
b10 !
b10 %
1"
#390
0"
#395
b11 !
b11 %
1"
#400
0"
#405
b100 !
b100 %
1"
#410
0"
#415
b101 !
b101 %
1"
#420
0"
#425
b110 !
b110 %
1"
#430
0"
#435
b111 !
b111 %
1"
#440
0"
#445
b1000 !
b1000 %
1"
#450
0"
#455
b1001 !
b1001 %
1"
#460
0"
#465
b1010 !
b1010 %
1"
#470
0"
#475
b1011 !
b1011 %
1"
#480
0"
#485
b1100 !
b1100 %
1"
#490
0"
#495
b1101 !
b1101 %
1"
#500
0"
#505
b1110 !
b1110 %
1"
#510
0"
#515
b1111 !
b1111 %
1"
