Day_9/REGISTER/PISO REGISTER/piso.v
module piso(
 input clk,
 input rst,
 input [3:0]p_in,
 output reg s_out);
always @(posedge clk or posedge rst)begin
if(rst)
     s_out<=1'b0;
else
      s_out<=p_in;
end
endmodule

Day_9/REGISTER/PISO REGISTER/piso_tb.v
module piso_tb;
reg clk;
reg rst;
reg [3:0]p_in;
wire s_out;
piso dut(.clk(clk),.rst(rst),.p_in(p_in),.s_out(s_out));
always #5 clk=~clk;
initial begin
$monitor("p_in=%b | s_out=%b | time=%0t",p_in,s_out,$time);
$dumpfile("piso.vcd");
$dumpvars(0);
clk=0;
rst=1;
p_in=1010;#10;

rst=0;
p_in=4'b0000;#10;
p_in=4'b0001;#10;
p_in=4'b0010;#10;
p_in=4'b0011;#10;
p_in=4'b0100;#10;
p_in=4'b0101;#10;
p_in=4'b0110;#10;
p_in=4'b0111;#10;
p_in=4'b1000;#10;
p_in=4'b1001;#10;
$finish;
end
endmodule

Day_09/REGISTER/PISO REGISTER/piso.vcd
$date
	Fri Dec 26 02:07:45 2025
$end
$version
	Icarus Verilog
$end
$timescale
	1s
$end
$scope module piso_tb $end
$var wire 1 ! s_out $end
$var reg 1 " clk $end
$var reg 4 # p_in [3:0] $end
$var reg 1 $ rst $end
$scope module dut $end
$var wire 1 " clk $end
$var wire 4 % p_in [3:0] $end
$var wire 1 $ rst $end
$var reg 1 ! s_out $end
$upscope $end
$upscope $end
$enddefinitions $end
$comment Show the parameter values. $end
$dumpall
$end
#0
$dumpvars
b10 %
1$
b10 #
0"
0!
$end
#5
1"
#10
0"
b0 #
b0 %
0$
#15
1"
#20
0"
b1 #
b1 %
#25
1!
1"
#30
0"
b10 #
b10 %
#35
0!
1"
#40
0"
b11 #
b11 %
#45
1!
1"
#50
0"
b100 #
b100 %
#55
0!
1"
#60
0"
b101 #
b101 %
#65
1!
1"
#70
0"
b110 #
b110 %
#75
0!
1"
#80
0"
b111 #
b111 %
#85
1!
1"
#90
0"
b1000 #
b1000 %
#95
0!
1"
#100
0"
b1001 #
b1001 %
#105
1!
1"
