DAY_8/FLIPFLOP/SR_FLIPFLOP/sr_flipflop.v
module sr_ff(
input s,r,clk,rst,
output reg q,
output qn);
always @(posedge clk or posedge rst)begin
if (rst)
    q<=1'b0;
else begin
     case({s,r})
    2'b00:q<=q;
    2'b01:q<=1'b0;
    2'b10:q<=1'b1;
    2'b11:q<=~q;
endcase
end 
end
assign qn=~q;
endmodule

DAY_08/FLIPFLOP/SR_FLIPFLOP/sr_flipflop_tb.v
module sr_ff_tb;
reg s,r,clk,rst;
wire q,qn;
sr_ff dut(.s(s),.r(r),.clk(clk),.rst(rst),.q(q),.qn(qn));
always #5 clk=~clk;
initial begin
$monitor("s=%b | r=%b |q=%b | qn=%b | time=%0t",s,r,q,qn,$time);
$dumpfile("sr_ff.vcd");
$dumpvars(0);
clk=0;
rst=1;
s=0;
r=0;#10;
rst=0;
s=0;r=0;#10;
s=0;r=1;#10;
s=1;r=0;#10;
s=1;r=1;#10;
s=0;r=1;#10;
s=1;r=1;#10;
$finish;
end
endmodule

DAY_8/FLIPFLOP/SR_FLIPFLOP/sr_ff.vcd
$date
	Fri Dec 19 15:02:51 2025
$end
$version
	Icarus Verilog
$end
$timescale
	1s
$end
$scope module sr_ff_tb $end
$var wire 1 ! qn $end
$var wire 1 " q $end
$var reg 1 # clk $end
$var reg 1 $ r $end
$var reg 1 % rst $end
$var reg 1 & s $end
$scope module dut $end
$var wire 1 # clk $end
$var wire 1 ! qn $end
$var wire 1 $ r $end
$var wire 1 % rst $end
$var wire 1 & s $end
$var reg 1 " q $end
$upscope $end
$upscope $end
$enddefinitions $end
$comment Show the parameter values. $end
$dumpall
$end
#0
$dumpvars
0&
1%
0$
0#
0"
1!
$end
#5
1#
#10
0#
0%
#15
1#
#20
0#
1$
#25
1#
#30
0#
0$
1&
#35
0!
1"
1#
#40
0#
1$
#45
1!
0"
1#
#50
0#
0&
#55
1#
#60
0#
1&
#65
0!
1"
1#
