DAY_6/COMPARATORS/EVEN_PARITY_CHECKER/even_parity_checker.v
module even_parity_checker(
input [4:0]a,
output reg b);
always @(*)begin

	b=^a;
end
endmodule

DAY_06/COMPARATORS/EVEN_PARITY_CHECKER/even_parity_checker_tb.v
module even_parity_checker_tb;
reg [4:0]a;
wire b;
even_parity_checker dut(.a(a),.b(b));
always @(a*b)begin
	if(b)
           $monitor("time=%t | a=%b | b=%b-ERROR",$time,a,b);
   else
	   $monitor("time=%t | a=%b | b=%b-NOERROR",$time,a,b);
   end
   initial begin
	   $dumpfile("even_parity_checker.vcd");
	   $dumpvars(0);
	   for(integer i=0;i<2**5;i++) begin
		   a=i;#15;
	   end
	   $finish;
   end
   endmodule

DAY_5/ENCODER/EVEN_PARITY_CHECKER/even_parity_checker.vcd
$date
	Fri Dec 12 12:40:05 2025
$end
$version
	Icarus Verilog
$end
$timescale
	1s
$end
$scope module even_parity_checker_tb $end
$var wire 1 ! b $end
$var reg 5 " a [4:0] $end
$scope module dut $end
$var wire 5 # a [4:0] $end
$var reg 1 ! b $end
$upscope $end
$scope begin $ivl_for_loop0 $end
$var integer 32 $ i [31:0] $end
$upscope $end
$upscope $end
$enddefinitions $end
$comment Show the parameter values. $end
$dumpall
$end
#0
$dumpvars
b0 $
b0 #
b0 "
0!
$end
#15
1!
b1 "
b1 #
b1 $
#30
b10 "
b10 #
b10 $
#45
0!
b11 "
b11 #
b11 $
#60
1!
b100 "
b100 #
b100 $
#75
0!
b101 "
b101 #
b101 $
#90
b110 "
b110 #
b110 $
#105
1!
b111 "
b111 #
b111 $
#120
b1000 "
b1000 #
b1000 $
#135
0!
b1001 "
b1001 #
b1001 $
#150
b1010 "
b1010 #
b1010 $
#165
1!
b1011 "
b1011 #
b1011 $
#180
0!
b1100 "
b1100 #
b1100 $
#195
1!
b1101 "
b1101 #
b1101 $
#210
b1110 "
b1110 #
b1110 $
#225
0!
b1111 "
b1111 #
b1111 $
#240
1!
b10000 "
b10000 #
b10000 $
#255
0!
b10001 "
b10001 #
b10001 $
#270
b10010 "
b10010 #
b10010 $
#285
1!
b10011 "
b10011 #
b10011 $
#300
0!
b10100 "
b10100 #
b10100 $
#315
1!
b10101 "
b10101 #
b10101 $
#330
b10110 "
b10110 #
b10110 $
#345
0!
b10111 "
b10111 #
b10111 $
#360
b11000 "
b11000 #
b11000 $
#375
1!
b11001 "
b11001 #
b11001 $
#390
b11010 "
b11010 #
b11010 $
#405
0!
b11011 "
b11011 #
b11011 $
#420
1!
b11100 "
b11100 #
b11100 $
#435
0!
b11101 "
b11101 #
b11101 $
#450
b11110 "
b11110 #
b11110 $
#465
1!
b11111 "
b11111 #
b11111 $
#480
b100000 $
