DAY_6/CODE  CONVERTER/GRAYCODE_TO_BINARY/graycode_to_binary.v
module gray_to_binary(
input [3:0]a,
output reg [3:0]b);
always @(*)begin
b[3]=a[3];
b[2]=a[3]^a[2];
b[1]=a[2]^a[1];
b[0]=a[1]^a[0];
end
endmodule

DAY_6/CODE  CONVERTER/GRAYCODE_TO_BINARY/graycode_to_binary_tb.v
module gray_to_binary_tb;
reg  [3:0]a;
wire [3:0]b;
gray_to_binary dut(.a(a),.b(b));
initial begin
$monitor("Time=%0t | a=%b | b=%b", $time,a,b);
$dumpfile("gray_to_binary.vcd");
$dumpvars;
a=4'b0000;#5;
a=4'b0001;#5;
a=4'b0010;#5; 
a=4'b0011;#5;
a=4'b1100;#5; 
a=4'b0101;#5;
a=4'b1010;#5; 
a=4'b1111;#5;
$finish;
end
endmodule

DAY_06/CODE  CONVERTER/GRAYCODE_TO_BINARY/gray_to_binary.vcd
$date
	Fri Dec 12 14:34:25 2025
$end
$version
	Icarus Verilog
$end
$timescale
	1s
$end
$scope module gray_to_binary_tb $end
$var wire 4 ! b [3:0] $end
$var reg 4 " a [3:0] $end
$scope module dut $end
$var wire 4 # a [3:0] $end
$var reg 4 $ b [3:0] $end
$upscope $end
$upscope $end
$enddefinitions $end
$comment Show the parameter values. $end
$dumpall
$end
#0
$dumpvars
b0 $
b0 #
b0 "
b0 !
$end
#5
b1 !
b1 $
b1 "
b1 #
#10
b11 !
b11 $
b10 "
b10 #
#15
b10 !
b10 $
b11 "
b11 #
#20
b1010 !
b1010 $
b1100 "
b1100 #
#25
b111 !
b111 $
b101 "
b101 #
#30
b1111 !
b1111 $
b1010 "
b1010 #
#35
b1000 !
b1000 $
b1111 "
b1111 #
