Day_9/REGISTER/SIPO REGISTER/sipo.v
module sipo#(
parameter WIDTH=4)
(input clk,
 input rst,
 input s_in,
 output wire [3:0]p_out);
 reg[WIDTH-1:0]shift_reg;
always @(posedge clk)begin
if(rst)
     shift_reg<={WIDTH{1'b0}};
else
      shift_reg<={shift_reg[WIDTH-2:0],s_in};
end
assign p_out[3:0]=shift_reg[WIDTH-1];
endmodule

Day_09/REGISTER/SIPO REGISTER/sipo_tb.v
module sipo_tb;
parameter WIDTH=4;
reg clk;
reg rst;
reg s_in;
wire [WIDTH-1:0]p_out;
sipo #(.WIDTH(WIDTH)) dut(.clk(clk),.rst(rst),.s_in(s_in),.p_out(p_out));
always #5 clk=~clk;
initial begin
$monitor("s_in=%b | p_out=%b | time=%0t",s_in,p_out,$time);
$dumpfile("sipo.vcd");
$dumpvars(0);
clk=0;
rst=1;
s_in=0;#10;

rst=0;
s_in=0;#10;
s_in=1;#10;
s_in=0;#10;
s_in=1;#10;
s_in=0;#10;
s_in=1;#10;
s_in=0;#10;
s_in=1;#10;
s_in=0;#10;
s_in=1;#10;
$finish;
end
endmodule

Day_9/REGISTER/SIPO REGISTER/sipo.vcd
$date
	Thu Dec 25 18:44:10 2025
$end
$version
	Icarus Verilog
$end
$timescale
	1s
$end
$scope module sipo_tb $end
$var wire 4 ! p_out [3:0] $end
$var parameter 32 " WIDTH $end
$var reg 1 # clk $end
$var reg 1 $ rst $end
$var reg 1 % s_in $end
$scope module dut $end
$var wire 1 # clk $end
$var wire 1 $ rst $end
$var wire 1 % s_in $end
$var wire 4 & p_out [3:0] $end
$var parameter 32 ' WIDTH $end
$var reg 4 ( shift_reg [3:0] $end
$upscope $end
$upscope $end
$enddefinitions $end
$comment Show the parameter values. $end
$dumpall
b100 '
b100 "
$end
#0
$dumpvars
bx (
b0x &
0%
1$
0#
b0x !
$end
#5
b0 !
b0 &
b0 (
1#
#10
0#
0$
#15
1#
#20
0#
1%
#25
b1 (
1#
#30
0#
0%
#35
b10 (
1#
#40
0#
1%
#45
b101 (
1#
#50
0#
0%
#55
b1 !
b1 &
b1010 (
1#
#60
0#
1%
#65
b0 !
b0 &
b101 (
1#
#70
0#
0%
#75
b1 !
b1 &
b1010 (
1#
#80
0#
1%
#85
b0 !
b0 &
b101 (
1#
#90
0#
0%
#95
b1 !
b1 &
b1010 (
1#
#100
0#
1%
#105
b0 !
b0 &
b101 (
1#
