DAY_5/ENCODER/encoder8x3/encoder8x3.v
module encoder8x3(
input [7:0]a,
output reg [2:0]b);
always @(*)begin
case(a)
8'b00000001:b=3'b000;
8'b00000010:b=3'b001;
8'b00000100:b=3'b010;
8'b00001000:b=3'b011;
8'b00010000:b=3'b100;
8'b00100000:b=3'b101;
8'b01000000:b=3'b110;
8'b10000000:b=3'b111;
default b=3'b000;
endcase
end
endmodule

DAY_5/ENCODER/encoder8x3/encoder8x3_tb.v
module encoder8x3_tb;
reg [7:0]a;
wire [2:0]b;
encoder8x3 dut(.a(a),.b(b));
initial begin
$monitor("time=%0t | a=%b |b=%b",$time,a,b);
$dumpfile("encoder8x3.vcd");
$dumpvars(0);
a=8'b00000001;#10;
a=8'b00000010;#10;
a=8'b00000100;#10;
a=8'b00001000;#10;
a=8'b00010000;#10;
a=8'b00100000;#10;
a=8'b01000000;#10;
a=8'b10000000;#10;
$finish;
end 
endmodule

DAY_05/ENCODER/encoder8x3/encoder8x3.vcd
$date
	Fri Dec 12 10:24:16 2025
$end
$version
	Icarus Verilog
$end
$timescale
	1s
$end
$scope module encoder8x3_tb $end
$var wire 3 ! b [2:0] $end
$var reg 8 " a [7:0] $end
$scope module dut $end
$var wire 8 # a [7:0] $end
$var reg 3 $ b [2:0] $end
$upscope $end
$upscope $end
$enddefinitions $end
$comment Show the parameter values. $end
$dumpall
$end
#0
$dumpvars
b0 $
b1 #
b1 "
b0 !
$end
#10
b1 !
b1 $
b10 "
b10 #
#20
b10 !
b10 $
b100 "
b100 #
#30
b11 !
b11 $
b1000 "
b1000 #
#40
b100 !
b100 $
b10000 "
b10000 #
#50
b101 !
b101 $
b100000 "
b100000 #
#60
b110 !
b110 $
b1000000 "
b1000000 #
#70
b111 !
b111 $
b10000000 "
b10000000 #
