DAY_1O/COUNTERS/UP COUNTER/up_counter.v
module up_counter(
 input clk,
 input rst,
 output reg [3:0]count);
always @(posedge clk or posedge rst)begin
if(rst)
     count<=4'b0000;
else
      count<=count+1'b1;
end
endmodule

DAY_10/COUNTERS/UP COUNTER/up_counter_tb.v
module up_counter_tb;
reg clk;
reg rst;
wire [3:0]count;
up_counter dut(.clk(clk),.rst(rst),.count(count));
always #5 clk=~clk;
initial begin
$dumpfile("up_counter.vcd");
$dumpvars(0,up_counter_tb);
clk=0;
rst=1;#10;

rst=0;

$monitor("count=%b | time=%0t",count,$time);

#100 $finish;

end
endmodule

DAY_1O/COUNTERS/UP COUNTER/up_counter.vcd
$date
	Fri Dec 26 03:04:34 2025
$end
$version
	Icarus Verilog
$end
$timescale
	1s
$end
$scope module up_counter_tb $end
$var wire 4 ! count [3:0] $end
$var reg 1 " clk $end
$var reg 1 # rst $end
$scope module dut $end
$var wire 1 " clk $end
$var wire 1 # rst $end
$var reg 4 $ count [3:0] $end
$upscope $end
$upscope $end
$enddefinitions $end
$comment Show the parameter values. $end
$dumpall
$end
#0
$dumpvars
b0 $
1#
0"
b0 !
$end
#5
1"
#10
0"
0#
#15
b1 !
b1 $
1"
#20
0"
#25
b10 !
b10 $
1"
#30
0"
#35
b11 !
b11 $
1"
#40
0"
#45
b100 !
b100 $
1"
#50
0"
#55
b101 !
b101 $
1"
#60
0"
#65
b110 !
b110 $
1"
#70
0"
#75
b111 !
b111 $
1"
#80
0"
#85
b1000 !
b1000 $
1"
#90
0"
#95
b1001 !
b1001 $
1"
#100
0"
#105
b1010 !
b1010 $
1"
