DAY_5/ENCODER/encoder16x4/encoder16x4.v
module encoder16x4(
input [15:0]a,
output reg  [3:0]b);
always @(*)begin
case(a)
16'b0000000000000001:b=4'b0000;
16'b0000000000000010:b=4'b0001;
16'b0000000000000100:b=4'b0010;
16'b0000000000001000:b=4'b0011;
16'b0000000000010000:b=4'b0100;
16'b0000000000100000:b=4'b0101;
16'b0000000001000000:b=4'b0110;
16'b0000000010000000:b=4'b0111;
16'b0000000100000000:b=4'b1000;
16'b0000001000000000:b=4'b1001;
16'b0000010000000000:b=4'b1010;
16'b0000100000000000:b=4'b1011;
16'b0001000000000000:b=4'b1100;
16'b0010000000000000:b=4'b1101;
16'b0100000000000000:b=4'b1110;
16'b1000000000000000:b=4'b1111;
default b=4'b000;
endcase
end
endmodule

DAY_05/ENCODER/encoder16x4/encoder16x4_tb.v
module encoder16x4_tb;
reg [15:0]a;
wire [3:0]b;
encoder16x4 dut(.a(a),.b(b));
initial begin
$monitor("time=%t | a=%b | b=%b",$time,a,b);
$dumpfile("encoder16x4.vcd");
$dumpvars(0);
a=16'b0000000000000001;#10;
a=16'b0000000000000010;#10;
a=16'b0000000000000100;#10;
a=16'b0000000000001000;#10;
a=16'b0000000000010000;#10;
a=16'b0000000000100000;#10;
a=16'b0000000001000000;#10;
a=16'b0000000010000000;#10;
a=16'b0000000100000000;#10;
a=16'b0000001000000000;#10;
a=16'b0000010000000000;#10;
a=16'b0000100000000000;#10;
a=16'b0001000000000000;#10;
a=16'b0010000000000000;#10;
a=16'b0100000000000000;#10;
a=16'b1000000000000000;#10;
$finish;
end
endmodule

DAY_05/ENCODER/encoder16x4/encoder16x4.vcd
$date
	Fri Dec 12 10:49:12 2025
$end
$version
	Icarus Verilog
$end
$timescale
	1s
$end
$scope module encoder16x4_tb $end
$var wire 4 ! b [3:0] $end
$var reg 16 " a [15:0] $end
$scope module dut $end
$var wire 16 # a [15:0] $end
$var reg 4 $ b [3:0] $end
$upscope $end
$upscope $end
$enddefinitions $end
$comment Show the parameter values. $end
$dumpall
$end
#0
$dumpvars
b0 $
b1 #
b1 "
b0 !
$end
#10
b1 !
b1 $
b10 "
b10 #
#20
b10 !
b10 $
b100 "
b100 #
#30
b11 !
b11 $
b1000 "
b1000 #
#40
b100 !
b100 $
b10000 "
b10000 #
#50
b101 !
b101 $
b100000 "
b100000 #
#60
b110 !
b110 $
b1000000 "
b1000000 #
#70
b111 !
b111 $
b10000000 "
b10000000 #
#80
b1000 !
b1000 $
b100000000 "
b100000000 #
#90
b1001 !
b1001 $
b1000000000 "
b1000000000 #
#100
b1010 !
b1010 $
b10000000000 "
b10000000000 #
#110
b1011 !
b1011 $
b100000000000 "
b100000000000 #
#120
b1100 !
b1100 $
b1000000000000 "
b1000000000000 #
#130
b1101 !
b1101 $
b10000000000000 "
b10000000000000 #
#140
b1110 !
b1110 $
b100000000000000 "
b100000000000000 #
#150
b1111 !
b1111 $
b1000000000000000 "
b1000000000000000 #
