DAY_05/DECODER/DECODER3X8/decoder3x8.v
module decoder3x8(
input [2:0]a,
output reg [7:0]b);
always @(*)begin
case(a)
3'b000:b=8'b00000001;
3'b001:b=8'b00000010;
3'b010:b=8'b00000100;
3'b011:b=8'b00001000;
3'b100:b=8'b00010000;
3'b101:b=8'b00100000;
3'b110:b=8'b01000000;
3'b111:b=8'b10000000;
endcase
end
endmodule

DAY_05/DECODER/DECODER3X8/decoder3x8_tb.v
module decoder3x8tb;
wire [7:0]b;
reg [2:0]a;
decoder3x8 dut(.a(a),.b(b));
initial begin
$monitor("Time=%0t | a=%b |  b=%b |(b[7]=%b | b[6]=%b | b[5]=%b | b[4]=%b | b[3]=%b | b[2]=%b | b[1]=%b | b[0]=%b )",$time,a,b,b[7],b[6],b[5],b[4],b[3],b[2],b[1],b[0]);
$dumpfile("decoder3x8.vcd");
$dumpvars(0);
a = 3'b000; #5;
a = 3'b001; #5;
a = 3'b010; #5;
a = 3'b011; #5;
a = 3'b100; #5;
a = 3'b101; #5;
a = 3'b110; #5;
a = 3'b111; #5;
$finish;
end
endmodule

DAY_5/DECODER/DECODER3X8/decoder3x8.vcd
$date
	Fri Dec 12 17:00:23 2025
$end
$version
	Icarus Verilog
$end
$timescale
	1s
$end
$scope module decoder3x8tb $end
$var wire 8 ! b [7:0] $end
$var reg 3 " a [2:0] $end
$scope module dut $end
$var wire 3 # a [2:0] $end
$var reg 8 $ b [7:0] $end
$upscope $end
$upscope $end
$enddefinitions $end
$comment Show the parameter values. $end
$dumpall
$end
#0
$dumpvars
b1 $
b0 #
b0 "
b1 !
$end
#5
b10 !
b10 $
b1 "
b1 #
#10
b100 !
b100 $
b10 "
b10 #
#15
b1000 !
b1000 $
b11 "
b11 #
#20
b10000 !
b10000 $
b100 "
b100 #
#25
b100000 !
b100000 $
b101 "
b101 #
#30
b1000000 !
b1000000 $
b110 "
b110 #
#35
b10000000 !
b10000000 $
b111 "
b111 #
